findwatt/__init__.py
findwatt/catalogs.py
findwatt/client.py
findwatt/datasets.py
findwatt/exceptions.py
findwatt/uploads.py
findwatt-1.0.2.dist-info/METADATA
findwatt-1.0.2.dist-info/RECORD
findwatt-1.0.2.dist-info/WHEEL
findwatt-1.0.2.dist-info/top_level.txt
tests/__init__.py
tests/test_catalogs.py
tests/test_client.py
tests/test_datasets.py
tests/test_uploads.py
