Metadata-Version: 2.1
Name: findwatt
Version: 1.0.2
Summary: Python client for FindWAtt's API
Home-page: https://bitbucket.org/FwPyClassification/findwatt-python
Author: FindWAtt
Author-email: luis@findwatt.com
License: UNKNOWN
Platform: any
Classifier: Programming Language :: Python :: 3.5
Classifier: Programming Language :: Python :: 3.6
Classifier: Programming Language :: Python :: 3.7
Classifier: License :: OSI Approved :: MIT License
Classifier: Operating System :: OS Independent
Requires-Dist: requests (<3.0.0,>=2.18.4)
Requires-Dist: marshmallow (<3.0.0,>=2.15.2)
